README.md
setup.py
tenable_jira/__init__.py
tenable_jira/cli.py
tenable_jira/config.py
tenable_jira/transform.py
tenable_jira/utils.py
tenable_jira/jira/__init__.py
tenable_jira/jira/fields.py
tenable_jira/jira/issues.py
tenable_jira/jira/issuetypes.py
tenable_jira/jira/projects.py
tenable_jira/jira/screens.py
tenable_jira_cloud.egg-info/PKG-INFO
tenable_jira_cloud.egg-info/SOURCES.txt
tenable_jira_cloud.egg-info/dependency_links.txt
tenable_jira_cloud.egg-info/entry_points.txt
tenable_jira_cloud.egg-info/requires.txt
tenable_jira_cloud.egg-info/top_level.txt