Metadata-Version: 1.1
Name: tenable-jira-cloud
Version: 1.1.10
Summary: Tenable -> Jira Cloud Bridge
Home-page: https://github.com/tenable/integrations-jira-cloud
Author: Tenable, Inc.
Author-email: smcgrath@tenable.com
License: MIT
Keywords: tenable tenable_io ibm jira
Platform: UNKNOWN
Classifier: Development Status :: 4 - Beta
Classifier: Intended Audience :: Information Technology
Classifier: Topic :: System :: Networking
Classifier: Topic :: Other/Nonlisted Topic
Classifier: License :: OSI Approved :: MIT License
Classifier: Programming Language :: Python :: 3.6
Classifier: Programming Language :: Python :: 3.7
